bigdata_helper/__init__.py
bigdata_helper/codes.py
bigdata_helper-0.1.0.dist-info/licenses/LICENSE
bigdata_helper-0.1.0.dist-info/METADATA
bigdata_helper-0.1.0.dist-info/WHEEL
bigdata_helper-0.1.0.dist-info/top_level.txt
bigdata_helper-0.1.0.dist-info/RECORD
