Metadata-Version: 2.4
Name: bigdata-helper
Version: 0.1.0
Summary: A Python library containing Big Data practical codes for quick access
Author: Satyam Kale
License: MIT
Project-URL: Homepage, https://pypi.org/project/bigdata-helper/
Keywords: big data,exam,codes,snippets,education
Classifier: Programming Language :: Python :: 3
Classifier: License :: OSI Approved :: MIT License
Classifier: Operating System :: OS Independent
Requires-Python: >=3.8
License-File: LICENSE
Dynamic: license-file
